johansen/__init__.py
johansen/criticalValues.py
johansen/critical_values.py
johansen/demo.py
johansen/johan.py
johansen/johansen.py
johansen/loadUtilities.py
johansen/utilities.py
mean_reversion_util/__init__.py
mean_reversion_util/criticalValues.py
mean_reversion_util/johan.py
mean_reversion_util/loadUtilities.py
mean_reversion_util/reinforcedLearning.py
mean_reversion_util/utilities.py
mean_reversion_util-0.0.6.dist-info/LICENSE
mean_reversion_util-0.0.6.dist-info/METADATA
mean_reversion_util-0.0.6.dist-info/WHEEL
mean_reversion_util-0.0.6.dist-info/top_level.txt
mean_reversion_util-0.0.6.dist-info/RECORD
