Metadata-Version: 2.1
Name: mean-reversion-util
Version: 0.0.6
Summary: Time Series mean reversion utilities
Home-page: https://github.com/gjlr2000/johansen3.git
Author: Gerardo Lemus
Author-email: gerardo@alum.mit.edu
License: MIT
Platform: UNKNOWN
Classifier: License :: OSI Approved :: MIT License
Classifier: Programming Language :: Python :: 2
Classifier: Programming Language :: Python :: 2.7
Requires-Dist: scipy (>=0.18.0)
Requires-Dist: statsmodels (>=0.6.1)
Requires-Dist: numpy (>=1.11.1)
Requires-Dist: pandas (>=0.18.1)
